kx132.py
circuitpython_kx132-0.2.0.dist-info/LICENSE
circuitpython_kx132-0.2.0.dist-info/METADATA
circuitpython_kx132-0.2.0.dist-info/WHEEL
circuitpython_kx132-0.2.0.dist-info/top_level.txt
circuitpython_kx132-0.2.0.dist-info/RECORD
