Metadata-Version: 2.1
Name: circuitpython-kx132
Version: 0.2.0
Summary: CircuitPython Driver for the Kionix KX132 Accelerometer
Author-email: JDM <xxx@mailmeto.mozmail.com>
License: MIT
Project-URL: Homepage, https://github.com/jposada202020/CircuitPython_KX132
Keywords: sensor,blinka,circuitpython,micropython,kx132,acceleration,gravity,accelerometer,sensor,driver,KX132
Classifier: Intended Audience :: Developers
Classifier: Topic :: Software Development :: Libraries
Classifier: Topic :: Software Development :: Embedded Systems
Classifier: Topic :: System :: Hardware
Classifier: License :: OSI Approved :: MIT License
Classifier: Programming Language :: Python :: 3
License-File: LICENSE
Requires-Dist: Adafruit-Blinka
Requires-Dist: adafruit-circuitpython-busdevice
Requires-Dist: adafruit-circuitpython-register
Provides-Extra: optional
